trt_sdk/__init__.py
trt_sdk/engine_trt8.0.so
trt_sdk/engine_trt8.2.so
trt_sdk/engine_trt8.4.so
trt_sdk-0.0.3.dist-info/METADATA
trt_sdk-0.0.3.dist-info/WHEEL
trt_sdk-0.0.3.dist-info/top_level.txt
trt_sdk-0.0.3.dist-info/RECORD
